{
    "Filename": "98685.txt",
    "Location": "Rio Vista, California",
    "Accident Number": "GAA19CA075",
    "Date & Time": "November 26, 2018, 12:30 Local",
    "Aircraft": "Darren M. Vinelli Sopwith PUP",
    "Registration": "N1916Z",
    "Flight Conducted Under": "Part 91: General aviation - Personal",
    "Aircraft Damage": "Substantial",
    "Defining Event": "Loss of control on ground",
    "Injuries": "1 None",
    "Analysis": {
        "Text": "pilot tailwheelequipped airplane reported landing airplane encountered variable crosswind gust left wing lifted able keep airplane runway established landing roll ground speed 20 mph airplane encountered another wind gust airplane weathervaned left exited left side runway rolled mud nosed airplane sustained substantial damage rudder pilot reported mechanical malfunction failure airplane would precluded normal operation pilot reported wind time accident variable 5 knot gusting 8 knot metar nearest airport 12 mile west accident site reported time accident wind 020 6 knot pilot landed airplane runway 25 probable cause finding national transportation safety board determines probable cause accident pilot failure maintain directional control landing roll gusting tailwind condition",
        "Top Words": [
            [
                "airplane",
                8
            ],
            [
                "pilot",
                5
            ],
            [
                "reported",
                4
            ]
        ]
    }
}